pelican_resume/__init__.py
pelican_resume/resume.py
pelican_resume/static/css/moderncv.css
pelican_resume-0.1.0.dist-info/DESCRIPTION.rst
pelican_resume-0.1.0.dist-info/METADATA
pelican_resume-0.1.0.dist-info/RECORD
pelican_resume-0.1.0.dist-info/WHEEL
pelican_resume-0.1.0.dist-info/metadata.json
pelican_resume-0.1.0.dist-info/top_level.txt
