Metadata-Version: 2.0
Name: pelican-resume
Version: 0.1.0
Summary: Easily generate customizable PDF resumes from Pelican pages
Home-page: https://github.com/cmenguy/pelican-resume
Author: Charles Menguy
Author-email: menguy.charles@gmail.com
License: MIT
Download-URL: https://github.com/cmenguy/pelican-resume/archive/0.1.0.zip
Keywords: pelican markdown blog resume pdf
Platform: UNKNOWN
Classifier: Development Status :: 5 - Production/Stable
Classifier: Operating System :: OS Independent
Classifier: Programming Language :: Python
Classifier: Programming Language :: Python :: 2.6
Classifier: Programming Language :: Python :: 2.7
Classifier: Intended Audience :: Developers
Classifier: License :: OSI Approved :: MIT License
Classifier: Topic :: Internet :: WWW/HTTP
Classifier: Topic :: Software Development :: Libraries :: Python Modules
Classifier: Topic :: Text Processing
Requires-Dist: pelican
